openconnect_lite/__init__.py
openconnect_lite/app.py
openconnect_lite/authenticator.py
openconnect_lite/cli.py
openconnect_lite/config.py
openconnect_lite/profile.py
openconnect_lite/saml_authenticator.py
openconnect_lite/version.py
openconnect_lite/browser/__init__.py
openconnect_lite/browser/browser.py
openconnect_lite/browser/user.js
openconnect_lite/browser/webengine_process.py
openconnect_lite-0.8.7.dist-info/METADATA
openconnect_lite-0.8.7.dist-info/WHEEL
openconnect_lite-0.8.7.dist-info/entry_points.txt
openconnect_lite-0.8.7.dist-info/licenses/LICENSE
openconnect_lite-0.8.7.dist-info/RECORD
