Metadata-Version: 2.4
Name: openconnect-lite
Version: 0.8.7
Summary: OpenConnect supporting Two-factor authentication (2FA) to Cisco SSL-VPNs
Project-URL: Homepage, https://github.com/kowyo/openconnect-lite
Project-URL: Documentation, https://github.com/kowyo/openconnect-lite#readme
Project-URL: Repository, https://github.com/kowyo/openconnect-lite.git
Author-email: Kowyo <kowyo@outlook.com>, László Vaskó <laszlo.vasko@outlook.com>
Maintainer-email: Kowyo <kowyo@outlook.com>
License-Expression: GPL-3.0-only
License-File: LICENSE
Requires-Python: >=3.14
Requires-Dist: attrs>=25.3.0
Requires-Dist: colorama>=0.4.6
Requires-Dist: keyring>=25.6.0
Requires-Dist: lxml>=6.0.2
Requires-Dist: prompt-toolkit>=3.0.52
Requires-Dist: pyotp>=2.9.0
Requires-Dist: pyqt6-webengine>=6.9.0
Requires-Dist: pyqt6>=6.9.1
Requires-Dist: pysocks>=1.7.1
Requires-Dist: pyxdg>=0.28
Requires-Dist: requests>=2.32.5
Requires-Dist: setuptools>=80.9.0
Requires-Dist: structlog>=25.4.0
Requires-Dist: toml>=0.10.2
